<?xml version="1.0" encoding="utf-8"?>
<cms.contentrelationshipitem>
  <ContentRelationshipItemGUID>ce11cecc-7001-4b03-8ede-59d16b865011</ContentRelationshipItemGUID>
  <ContentRelationshipItemObjectID>
    <CodeName>/Cookie-Policy</CodeName>
    <GUID>10837f11-c459-4bf6-b707-783adcb34c0d</GUID>
    <ObjectType>cms.node</ObjectType>
    <Site>
      <CodeName>KBank</CodeName>
      <GUID>ee71668e-9013-4bce-81f2-c1e91a2bca73</GUID>
      <ObjectType>cms.site</ObjectType>
    </Site>
  </ContentRelationshipItemObjectID>
  <ContentRelationshipItemObjectType>cms.node</ContentRelationshipItemObjectType>
  <ContentRelationshipItemSiteID>
    <CodeName>KBank</CodeName>
    <GUID>ee71668e-9013-4bce-81f2-c1e91a2bca73</GUID>
    <ObjectType>cms.site</ObjectType>
  </ContentRelationshipItemSiteID>
</cms.contentrelationshipitem>