<?xml version="1.0" encoding="utf-8"?>
<cms.consent>
  <ConsentContent>
    <ConsentContent xmlns:i="http://www.w3.org/2001/XMLSchema-instance">
      <ConsentLanguageVersions>
        <ConsentLanguageVersion>
          <FullText>
            <![CDATA[<p>Marketing cookies and the data you provide us allow us to link our website to third-party social media and advertising networks, such as Facebook or Google Ads. With this connection, we can present relevant ads outside our website.</p>]]>
          </FullText>
          <LanguageName>en</LanguageName>
          <ShortText>
            <![CDATA[<p>Marketing cookies are used to provide relevant ads based on your activity</p>]]>
          </ShortText>
        </ConsentLanguageVersion>
        <ConsentLanguageVersion>
          <FullText>
            <![CDATA[<p>Las cookies de marketing y los datos que usted nos proporciona nos permiten vincular nuestro sitio web a redes sociales y publicitarias de terceros, como Facebook o Google Ads. Con esta conexión podemos presentar anuncios relevantes fuera de nuestro sitio web.</p>]]>
          </FullText>
          <LanguageName>es</LanguageName>
          <ShortText>
            <![CDATA[<p>Las cookies de marketing se utilizan para proporcionar anuncios relevantes según su actividad.</p>]]>
          </ShortText>
        </ConsentLanguageVersion>
      </ConsentLanguageVersions>
    </ConsentContent>
  </ConsentContent>
  <ConsentDisplayName>Marketing cookies</ConsentDisplayName>
  <ConsentGuid>f12a51d0-322d-44d3-a8cc-ac29d760750e</ConsentGuid>
  <ConsentHash>
    <![CDATA[a1058edc88eb35ff88ca8a433977e5309b176b7ed1d8ff4ddf58dd64213d9b50]]>
  </ConsentHash>
  <ConsentName>marketing.cookies.consent</ConsentName>
</cms.consent>