<?xml version="1.0" encoding="utf-8"?>
<cms.contentitem>
  <ContentItemContentFolderID>
    <CodeName>Root</CodeName>
    <GUID>9d6509a4-a231-4837-8f1c-81a90705f988</GUID>
    <ObjectType>cms.contentfolder</ObjectType>
  </ContentItemContentFolderID>
  <ContentItemContentTypeID>
    <CodeName>TrainingGuides.PetFoodFormulation</CodeName>
    <GUID>a69ed0b4-65d3-459e-847a-2b65e2f82a5a</GUID>
    <ObjectType>cms.contenttype</ObjectType>
  </ContentItemContentTypeID>
  <ContentItemGUID>b1091d81-bbbd-405e-91c7-c67b7706da20</ContentItemGUID>
  <ContentItemIsReusable>True</ContentItemIsReusable>
  <ContentItemIsSecured>False</ContentItemIsSecured>
  <ContentItemName>PurremoEssentialsDryCatFood-SalmonAndRice-c2672mjk</ContentItemName>
  <ContentItemWorkspaceID>
    <CodeName>KenticoDefault</CodeName>
    <GUID>43f674d6-540d-4f91-8c19-608b5bddb2f2</GUID>
    <ObjectType>cms.workspace</ObjectType>
  </ContentItemWorkspaceID>
</cms.contentitem>