<?xml version="1.0" encoding="utf-8"?>
<cms.contentitem>
  <ContentItemContentTypeID>
    <CodeName>TrainingGuides.Asset</CodeName>
    <GUID>9ecde825-735e-4967-a995-cc97b55adb0f</GUID>
    <ObjectType>cms.contenttype</ObjectType>
  </ContentItemContentTypeID>
  <ContentItemGUID>d7b682e2-82fc-44ce-b434-590a9b2b0a7a</ContentItemGUID>
  <ContentItemIsReusable>True</ContentItemIsReusable>
  <ContentItemIsSecured>False</ContentItemIsSecured>
  <ContentItemName>Star2-p41ggao7</ContentItemName>
</cms.contentitem>