<?xml version="1.0" encoding="utf-8"?>
<cms.contentitem>
  <ContentItemContentFolderID>
    <CodeName>Root</CodeName>
    <GUID>9d6509a4-a231-4837-8f1c-81a90705f988</GUID>
    <ObjectType>cms.contentfolder</ObjectType>
  </ContentItemContentFolderID>
  <ContentItemContentTypeID>
    <CodeName>TrainingGuides.DogCollarVariant</CodeName>
    <GUID>ade8fcc8-e483-432a-ae37-2c2cc5bc640d</GUID>
    <ObjectType>cms.contenttype</ObjectType>
  </ContentItemContentTypeID>
  <ContentItemGUID>48cd8588-c886-4e58-a298-0db211ae1dbb</ContentItemGUID>
  <ContentItemIsReusable>True</ContentItemIsReusable>
  <ContentItemIsSecured>False</ContentItemIsSecured>
  <ContentItemName>TrailFlexReflectiveDogCollar-Blue-e6ut92gd</ContentItemName>
  <ContentItemWorkspaceID>
    <CodeName>KenticoDefault</CodeName>
    <GUID>43f674d6-540d-4f91-8c19-608b5bddb2f2</GUID>
    <ObjectType>cms.workspace</ObjectType>
  </ContentItemWorkspaceID>
</cms.contentitem>