<?xml version="1.0" encoding="utf-8"?>
<cms.contentitem>
  <ContentItemChannelID>
    <CodeName>TrainingGuidesPages</CodeName>
    <GUID>5ba9c1e8-b61e-4570-b666-87a9b92bbe3b</GUID>
    <ObjectType>cms.channel</ObjectType>
  </ContentItemChannelID>
  <ContentItemContentTypeID>
    <CodeName>TrainingGuides.StoreSection</CodeName>
    <GUID>5ce8de4d-0304-496a-8b09-7271613dd135</GUID>
    <ObjectType>cms.contenttype</ObjectType>
  </ContentItemContentTypeID>
  <ContentItemGUID>aa2f2b1a-dd24-4e83-91f1-cda4beff09a1</ContentItemGUID>
  <ContentItemIsReusable>False</ContentItemIsReusable>
  <ContentItemIsSecured>False</ContentItemIsSecured>
  <ContentItemName>DogCollar-5hrayy3u</ContentItemName>
</cms.contentitem>