<?xml version="1.0" encoding="utf-8"?>
<cms.webpageurlpath>
  <WebPageUrlPath>es/Store/Dog-collars</WebPageUrlPath>
  <WebPageUrlPathContentLanguageID>
    <CodeName>es</CodeName>
    <GUID>b2e99971-c2dd-4a47-bb64-0d9a0d28d226</GUID>
    <ObjectType>cms.contentlanguage</ObjectType>
  </WebPageUrlPathContentLanguageID>
  <WebPageUrlPathGUID>39c383d0-5946-4462-bff8-8d3b52f97a6e</WebPageUrlPathGUID>
  <WebPageUrlPathHash>
    <![CDATA[7C3357A15AFD6ADE5609F862A61DA78835E45909FA4151D19C88EE69EB3DC0E8]]>
  </WebPageUrlPathHash>
  <WebPageUrlPathIsCanonical>True</WebPageUrlPathIsCanonical>
  <WebPageUrlPathIsDraft>False</WebPageUrlPathIsDraft>
  <WebPageUrlPathIsLatest>True</WebPageUrlPathIsLatest>
  <WebPageUrlPathType>0</WebPageUrlPathType>
  <WebPageUrlPathWebPageItemID>
    <CodeName>DogCollars-azesj7o5</CodeName>
    <GUID>e65fddac-8919-49c8-b366-add2f5fc449d</GUID>
    <ObjectType>cms.webpageitem</ObjectType>
  </WebPageUrlPathWebPageItemID>
  <WebPageUrlPathWebsiteChannelID>
    <GUID>fdba40fe-1ece-4821-9d57-eaa1d89e13b1</GUID>
    <ObjectType>cms.websitechannel</ObjectType>
    <Parent>
      <CodeName>TrainingGuidesPages</CodeName>
      <GUID>5ba9c1e8-b61e-4570-b666-87a9b92bbe3b</GUID>
      <ObjectType>cms.channel</ObjectType>
    </Parent>
  </WebPageUrlPathWebsiteChannelID>
</cms.webpageurlpath>